INSTALL.rst
LICENSE
MANIFEST.in
README.rst
VERSION
requirements.txt
setup.py
tasks.py
src/game_of_life/__init__.py
src/game_of_life/__main__.py
src/game_of_life/__meta__.py
src/game_of_life/core.py
src/game_of_life.egg-info/PKG-INFO
src/game_of_life.egg-info/SOURCES.txt
src/game_of_life.egg-info/dependency_links.txt
src/game_of_life.egg-info/entry_points.txt
src/game_of_life.egg-info/not-zip-safe
src/game_of_life.egg-info/requires.txt
src/game_of_life.egg-info/top_level.txt
src/game_of_life/tests/__init__.py
src/game_of_life/tests/__main__.py
src/game_of_life/tests/test_documentation.py
src/game_of_life/tests/test_game_of_life.py